thlink_backend_db_lib/__init__.py
thlink_backend_db_lib/db.py
thlink_backend_db_lib-0.4.15.dist-info/LICENSE
thlink_backend_db_lib-0.4.15.dist-info/WHEEL
thlink_backend_db_lib-0.4.15.dist-info/METADATA
thlink_backend_db_lib-0.4.15.dist-info/RECORD
