Metadata-Version: 2.1
Name: thlink-backend-db-lib
Version: 0.4.15
Summary: Dynamodb Wrapper
Author: thlink
Requires-Python: >=3.7,<4.0
Classifier: Programming Language :: Python :: 3
Classifier: Programming Language :: Python :: 3.7
Classifier: Programming Language :: Python :: 3.8
Classifier: Programming Language :: Python :: 3.9
Requires-Dist: boto3 (>=1.17.78,<2.0.0)
Requires-Dist: circuitbreaker (>=1.3.1,<2.0.0)
